MANIFEST.in
README
distribute_setup.py
setup.py
src/django_qmanager.egg-info/PKG-INFO
src/django_qmanager.egg-info/SOURCES.txt
src/django_qmanager.egg-info/dependency_links.txt
src/django_qmanager.egg-info/top_level.txt
src/djqmgr/__init__.py