Metadata-Version: 1.0
Name: django-qmanager
Version: 0.1.1
Summary: Create managers for Django models based on pre-defined queries.
Home-page: http://bitbucket.org/zacharyvoase/django-qmanager
Author: Zachary Voase
Author-email: zacharyvoase@me.com
License: UNKNOWN
Platform: UNKNOWN
